bits/__init__.py
bits/smtp/__init__.py
bits_smtp-1.0.7.dist-info/METADATA
bits_smtp-1.0.7.dist-info/WHEEL
bits_smtp-1.0.7.dist-info/top_level.txt
bits_smtp-1.0.7.dist-info/RECORD
