Metadata-Version: 2.1
Name: bits-smtp
Version: 1.0.7
Summary: BITS SMTP
Home-page: UNKNOWN
Author: Lukas Karlsson
Author-email: karlsson@broadinstitute.org
License: Apache Software License
Platform: UNKNOWN
Requires-Dist: mailer
